science_optimization/__init__.py
science_optimization/algorithms/__init__.py
science_optimization/algorithms/base_algorithms.py
science_optimization/algorithms/cutting_plane/__init__.py
science_optimization/algorithms/cutting_plane/ellipsoid_method.py
science_optimization/algorithms/decomposition/__init__.py
science_optimization/algorithms/decomposition/dual_decomposition.py
science_optimization/algorithms/derivative_free/__init__.py
science_optimization/algorithms/derivative_free/nelder_mead.py
science_optimization/algorithms/lagrange/__init__.py
science_optimization/algorithms/lagrange/augmented_lagrangian.py
science_optimization/algorithms/linear_programming/__init__.py
science_optimization/algorithms/linear_programming/glop.py
science_optimization/algorithms/linear_programming/scipy_base_linear.py
science_optimization/algorithms/linear_programming/scipy_highs_method.py
science_optimization/algorithms/linear_programming/scipy_interior_point_method.py
science_optimization/algorithms/linear_programming/scipy_simplex_method.py
science_optimization/algorithms/search_direction/__init__.py
science_optimization/algorithms/search_direction/base_search_direction.py
science_optimization/algorithms/search_direction/gradient_algorithm.py
science_optimization/algorithms/search_direction/newton_algorithm.py
science_optimization/algorithms/search_direction/quasi_newton.py
science_optimization/algorithms/unidimensional/__init__.py
science_optimization/algorithms/unidimensional/base_unidimensional.py
science_optimization/algorithms/unidimensional/golden_section.py
science_optimization/algorithms/unidimensional/multimodal_golden_section.py
science_optimization/algorithms/utils/__init__.py
science_optimization/algorithms/utils/algorithms_utils.py
science_optimization/builder/__init__.py
science_optimization/builder/builder_optimization_problem.py
science_optimization/builder/constraint.py
science_optimization/builder/objective.py
science_optimization-9.0.3.dist-info/LICENSE
science_optimization-9.0.3.dist-info/METADATA
science_optimization-9.0.3.dist-info/WHEEL
science_optimization-9.0.3.dist-info/RECORD
