Metadata-Version: 2.1
Name: science-optimization
Version: 9.0.3
Summary: A framework for optimization.
Author: Matheus Mendonça
Author-email: matheus.mendonca@enacom.com.br
Requires-Python: >=3.8,<3.12
Classifier: Programming Language :: Python :: 3
Classifier: Programming Language :: Python :: 3.8
Classifier: Programming Language :: Python :: 3.9
Classifier: Programming Language :: Python :: 3.10
Classifier: Programming Language :: Python :: 3.11
Requires-Dist: cycler (>=0.11,<1.0)
Requires-Dist: decorator (>=5.1,<6.0)
Requires-Dist: joblib (>=1.1,<2.0)
Requires-Dist: kiwisolver (>=1.3,<2.0)
Requires-Dist: matplotlib (>=3.4,<4.0)
Requires-Dist: networkx (>=2.6,<3.0)
Requires-Dist: numpy (>=1.21,<2.0)
Requires-Dist: ortools (>=9.6,<10.0)
Requires-Dist: pandas (>=1.3,<2.0)
Requires-Dist: pillow (>=9.3,<10.0)
Requires-Dist: protobuf (>=4.22,<5.0)
Requires-Dist: pybind11 (>=2.10.4,<3.0.0)
Requires-Dist: pyparsing (>=3.0,<4.0)
Requires-Dist: python-dateutil (>=2.8,<3.0)
Requires-Dist: pytz (>=2021.3,<2022.0)
Requires-Dist: pywavelets (>=1.1,<2.0)
Requires-Dist: scipy (>=1.10,<2.0)
Requires-Dist: six (>=1.16,<2.0)
Requires-Dist: xlrd (>=2.0,<3.0)
